{
    "format": "json",
    "view": "page",
    "doc": "E40.xml",
    "root": "2.5.12.8.43.6.253",
    "rootNode": "2.5.12.8.43.6.253",
    "id": "Ed_133_id",
    "odd": "nietzsche-ed.odd",
    "next": "2.5.12.8.43.6.343",
    "previous": "2.5.12.8.43.6.159",
    "nextId": "Ed_134_id",
    "previousId": "Ed_132_id",
    "switchView": "2.5.12",
    "content": "<!DOCTYPE html><html><head></head><body><div class=\"content \"><div class=\"tei-div8\"></div></div></body></html>",
    "footnotes": "",
    "userParams": {
        "odd": "surface.odd",
        "webcomponents": 7,
        "type": "genesis",
        "mode": "querverweis"
    },
    "collection": ""
}